{
  "Top": "hls_LK",
  "RtlTop": "hls_LK",
  "RtlPrefix": "",
  "SourceLanguage": "cpp",
  "ResetStyle": "control",
  "GenerateBdFiles": "0",
  "HostMachineBits": "64",
  "Target": {
    "Family": "zynq",
    "Device": "xc7z100",
    "Package": "ffv900",
    "Speed": "-2"
  },
  "HlsSolution": {
    
  },
  "ClockInfo": {
    "ClockName": "ap_clk",
    "ClockPeriod": "10",
    "IsCombLogic": "0",
    "II": "x",
    "Latency": "307239",
    "Uncertainty": "0.1"
  },
  "Xdc": {"OocClocks": ["create_clock -name ap_clk -period 10.000 [get_ports ap_clk]"]},
  "Ipx": {
    "Vendor": "xilinx.com",
    "Library": "hls",
    "Name": "hls_LK",
    "Version": "1.0",
    "DisplayName": "Hls_lk",
    "Revision": "",
    "Description": "An IP generated by Vivado HLS",
    "Taxonomy": "\/VIVADO_HLS_IP"
  },
  "Files": {
    "CSource": [
      "..\/src\/motion_compensation.cpp",
      "..\/src\/ap_bmp.cpp",
      "..\/src\/LKof_ref.cpp",
      "..\/src\/LKof_hls_opt.cpp"
    ],
    "Vhdl": [
      "impl\/vhdl\/fifo_w12_d10_A.vhd",
      "impl\/vhdl\/fifo_w13_d10_A.vhd",
      "impl\/vhdl\/fifo_w16_d2_A.vhd",
      "impl\/vhdl\/fifo_w34_d10_A.vhd",
      "impl\/vhdl\/hls_ComputeIntegrals.vhd",
      "impl\/vhdl\/hls_ComputeIntegrpcA.vhd",
      "impl\/vhdl\/hls_ComputeVectors.vhd",
      "impl\/vhdl\/hls_isotropic_kernel.vhd",
      "impl\/vhdl\/hls_LK_am_addmul_ncg.vhd",
      "impl\/vhdl\/hls_LK_am_addmul_zec.vhd",
      "impl\/vhdl\/hls_LK_fdiv_32ns_Gfk.vhd",
      "impl\/vhdl\/hls_LK_fmul_32ns_Ffa.vhd",
      "impl\/vhdl\/hls_LK_mac_muladdBew.vhd",
      "impl\/vhdl\/hls_LK_mac_muladdCeG.vhd",
      "impl\/vhdl\/hls_LK_mac_muladdDeQ.vhd",
      "impl\/vhdl\/hls_LK_mac_muladdEe0.vhd",
      "impl\/vhdl\/hls_LK_mul_mul_13Aem.vhd",
      "impl\/vhdl\/hls_LK_mul_mul_16IfE.vhd",
      "impl\/vhdl\/hls_LK_mul_mul_19ocq.vhd",
      "impl\/vhdl\/hls_LK_sitofp_64nHfu.vhd",
      "impl\/vhdl\/hls_SpatialTemporalD.vhd",
      "impl\/vhdl\/hls_SpatialTemporjbC.vhd",
      "impl\/vhdl\/hls_twoIsotropicFbkb.vhd",
      "impl\/vhdl\/hls_twoIsotropicFilt.vhd",
      "impl\/vhdl\/start_for_hls_ComKfY.vhd",
      "impl\/vhdl\/start_for_hls_ComLf8.vhd",
      "impl\/vhdl\/start_for_hls_SpaJfO.vhd",
      "impl\/vhdl\/hls_LK.vhd"
    ],
    "Verilog": [
      "impl\/verilog\/fifo_w12_d10_A.v",
      "impl\/verilog\/fifo_w13_d10_A.v",
      "impl\/verilog\/fifo_w16_d2_A.v",
      "impl\/verilog\/fifo_w34_d10_A.v",
      "impl\/verilog\/hls_ComputeIntegrals.v",
      "impl\/verilog\/hls_ComputeIntegrpcA.v",
      "impl\/verilog\/hls_ComputeIntegrpcA_ram.dat",
      "impl\/verilog\/hls_ComputeVectors.v",
      "impl\/verilog\/hls_isotropic_kernel.v",
      "impl\/verilog\/hls_LK_am_addmul_ncg.v",
      "impl\/verilog\/hls_LK_am_addmul_zec.v",
      "impl\/verilog\/hls_LK_fdiv_32ns_Gfk.v",
      "impl\/verilog\/hls_LK_fmul_32ns_Ffa.v",
      "impl\/verilog\/hls_LK_mac_muladdBew.v",
      "impl\/verilog\/hls_LK_mac_muladdCeG.v",
      "impl\/verilog\/hls_LK_mac_muladdDeQ.v",
      "impl\/verilog\/hls_LK_mac_muladdEe0.v",
      "impl\/verilog\/hls_LK_mul_mul_13Aem.v",
      "impl\/verilog\/hls_LK_mul_mul_16IfE.v",
      "impl\/verilog\/hls_LK_mul_mul_19ocq.v",
      "impl\/verilog\/hls_LK_sitofp_64nHfu.v",
      "impl\/verilog\/hls_SpatialTemporalD.v",
      "impl\/verilog\/hls_SpatialTemporjbC.v",
      "impl\/verilog\/hls_SpatialTemporjbC_ram.dat",
      "impl\/verilog\/hls_twoIsotropicFbkb.v",
      "impl\/verilog\/hls_twoIsotropicFbkb_ram.dat",
      "impl\/verilog\/hls_twoIsotropicFilt.v",
      "impl\/verilog\/start_for_hls_ComKfY.v",
      "impl\/verilog\/start_for_hls_ComLf8.v",
      "impl\/verilog\/start_for_hls_SpaJfO.v",
      "impl\/verilog\/hls_LK.v"
    ],
    "Misc": ["impl\/misc\/logo.png"],
    "Subcore": [
      "impl\/misc\/hls_LK_ap_fdiv_8_no_dsp_32_ip.tcl",
      "impl\/misc\/hls_LK_ap_fmul_1_max_dsp_32_ip.tcl",
      "impl\/misc\/hls_LK_ap_sitofp_2_no_dsp_64_ip.tcl"
    ]
  },
  "SubcoreInfo": {
    "HasXpmMemory": false,
    "HasClockedDsp": false,
    "IP": [
      {
        "name": "hls_LK_ap_fdiv_8_no_dsp_32",
        "vlnv": "xilinx.com:ip:floating_point:7.1",
        "params": "CONFIG.a_precision_type Single CONFIG.a_tuser_width 1 CONFIG.add_sub_value Both CONFIG.b_tuser_width 1 CONFIG.c_a_exponent_width 8 CONFIG.c_a_fraction_width 24 CONFIG.c_compare_operation Programmable CONFIG.c_has_divide_by_zero false CONFIG.c_has_invalid_op false CONFIG.c_has_overflow false CONFIG.c_has_underflow false CONFIG.c_latency 8 CONFIG.c_mult_usage No_Usage CONFIG.c_optimization Speed_Optimized CONFIG.c_rate 1 CONFIG.c_result_exponent_width 8 CONFIG.c_result_fraction_width 24 CONFIG.component_name hls_LK_ap_fdiv_8_no_dsp_32 CONFIG.flow_control NonBlocking CONFIG.has_a_tlast false CONFIG.has_a_tuser false CONFIG.has_aclken true CONFIG.has_aresetn false CONFIG.has_b_tlast false CONFIG.has_b_tuser false CONFIG.has_operation_tlast false CONFIG.has_operation_tuser false CONFIG.has_result_tready false CONFIG.maximum_latency false CONFIG.operation_tuser_width 1 CONFIG.operation_type Divide CONFIG.result_precision_type Single CONFIG.result_tlast_behv Null"
      },
      {
        "name": "hls_LK_ap_fmul_1_max_dsp_32",
        "vlnv": "xilinx.com:ip:floating_point:7.1",
        "params": "CONFIG.a_precision_type Single CONFIG.a_tuser_width 1 CONFIG.add_sub_value Both CONFIG.b_tuser_width 1 CONFIG.c_a_exponent_width 8 CONFIG.c_a_fraction_width 24 CONFIG.c_compare_operation Programmable CONFIG.c_has_divide_by_zero false CONFIG.c_has_invalid_op false CONFIG.c_has_overflow false CONFIG.c_has_underflow false CONFIG.c_latency 1 CONFIG.c_mult_usage Max_Usage CONFIG.c_optimization Speed_Optimized CONFIG.c_rate 1 CONFIG.c_result_exponent_width 8 CONFIG.c_result_fraction_width 24 CONFIG.component_name hls_LK_ap_fmul_1_max_dsp_32 CONFIG.flow_control NonBlocking CONFIG.has_a_tlast false CONFIG.has_a_tuser false CONFIG.has_aclken true CONFIG.has_aresetn false CONFIG.has_b_tlast false CONFIG.has_b_tuser false CONFIG.has_operation_tlast false CONFIG.has_operation_tuser false CONFIG.has_result_tready false CONFIG.maximum_latency false CONFIG.operation_tuser_width 1 CONFIG.operation_type Multiply CONFIG.result_precision_type Single CONFIG.result_tlast_behv Null"
      },
      {
        "name": "hls_LK_ap_sitofp_2_no_dsp_64",
        "vlnv": "xilinx.com:ip:floating_point:7.1",
        "params": "CONFIG.a_precision_type Custom CONFIG.a_tuser_width 1 CONFIG.add_sub_value Both CONFIG.b_tuser_width 1 CONFIG.c_a_exponent_width 64 CONFIG.c_a_fraction_width 0 CONFIG.c_compare_operation Programmable CONFIG.c_has_divide_by_zero false CONFIG.c_has_invalid_op false CONFIG.c_has_overflow false CONFIG.c_has_underflow false CONFIG.c_latency 2 CONFIG.c_mult_usage No_Usage CONFIG.c_optimization Speed_Optimized CONFIG.c_rate 1 CONFIG.c_result_exponent_width 8 CONFIG.c_result_fraction_width 24 CONFIG.component_name hls_LK_ap_sitofp_2_no_dsp_64 CONFIG.flow_control NonBlocking CONFIG.has_a_tlast false CONFIG.has_a_tuser false CONFIG.has_aclken true CONFIG.has_aresetn false CONFIG.has_b_tlast false CONFIG.has_b_tuser false CONFIG.has_operation_tlast false CONFIG.has_operation_tuser false CONFIG.has_result_tready false CONFIG.maximum_latency false CONFIG.operation_tuser_width 1 CONFIG.operation_type Fixed_to_Float CONFIG.result_precision_type Single CONFIG.result_tlast_behv Null"
      }
    ]
  },
  "Interfaces": {
    "ap_clk": {
      "type": "clock",
      "ctype": {"CLK": {"Type": "bool"}},
      "reset": "ap_rst"
    },
    "ap_ctrl": {
      "type": "ap_ctrl",
      "ctrl_ports": "ap_done ap_start ap_ready ap_idle",
      "ctype": {
        "done": {"Type": "bool"},
        "start": {"Type": "bool"},
        "ready": {"Type": "bool"},
        "idle": {"Type": "bool"}
      }
    },
    "ap_return": {
      "type": "data",
      "dir": "out",
      "width": "32",
      "ctype": {"DATA": {
          "Type": "integer signed",
          "Width": "32"
        }}
    },
    "ap_rst": {
      "type": "reset",
      "polarity": "ACTIVE_HIGH",
      "ctype": {"RST": {"Type": "bool"}}
    },
    "height": {
      "type": "data",
      "dir": "in",
      "width": "16",
      "ctype": {"DATA": {
          "Type": "integer unsigned",
          "Width": "16"
        }}
    },
    "inp1_img": {
      "type": "ap_fifo",
      "fifo_width": "16",
      "fifo_type": "read",
      "ctype": {
        "RD_DATA": {
          "Type": "integer unsigned",
          "Width": "16"
        },
        "EMPTY_N": {"Type": "bool"},
        "RD_EN": {"Type": "bool"}
      }
    },
    "inp2_img": {
      "type": "ap_fifo",
      "fifo_width": "16",
      "fifo_type": "read",
      "ctype": {
        "RD_DATA": {
          "Type": "integer unsigned",
          "Width": "16"
        },
        "EMPTY_N": {"Type": "bool"},
        "RD_EN": {"Type": "bool"}
      }
    },
    "vx_img": {
      "type": "ap_fifo",
      "fifo_width": "16",
      "fifo_type": "write",
      "ctype": {
        "WR_DATA": {
          "Type": "integer signed",
          "Width": "16"
        },
        "FULL_N": {"Type": "bool"},
        "WR_EN": {"Type": "bool"}
      }
    },
    "vy_img": {
      "type": "ap_fifo",
      "fifo_width": "16",
      "fifo_type": "write",
      "ctype": {
        "WR_DATA": {
          "Type": "integer signed",
          "Width": "16"
        },
        "FULL_N": {"Type": "bool"},
        "WR_EN": {"Type": "bool"}
      }
    },
    "width": {
      "type": "data",
      "dir": "in",
      "width": "16",
      "ctype": {"DATA": {
          "Type": "integer unsigned",
          "Width": "16"
        }}
    }
  },
  "RtlPorts": {
    "inp1_img_dout": {
      "dir": "in",
      "width": "16"
    },
    "inp1_img_empty_n": {
      "dir": "in",
      "width": "1"
    },
    "inp1_img_read": {
      "dir": "out",
      "width": "1"
    },
    "inp2_img_dout": {
      "dir": "in",
      "width": "16"
    },
    "inp2_img_empty_n": {
      "dir": "in",
      "width": "1"
    },
    "inp2_img_read": {
      "dir": "out",
      "width": "1"
    },
    "vx_img_din": {
      "dir": "out",
      "width": "16"
    },
    "vx_img_full_n": {
      "dir": "in",
      "width": "1"
    },
    "vx_img_write": {
      "dir": "out",
      "width": "1"
    },
    "vy_img_din": {
      "dir": "out",
      "width": "16"
    },
    "vy_img_full_n": {
      "dir": "in",
      "width": "1"
    },
    "vy_img_write": {
      "dir": "out",
      "width": "1"
    },
    "height": {
      "dir": "in",
      "width": "16"
    },
    "width": {
      "dir": "in",
      "width": "16"
    },
    "ap_clk": {
      "dir": "in",
      "width": "1"
    },
    "ap_rst": {
      "dir": "in",
      "width": "1"
    },
    "ap_return": {
      "dir": "out",
      "width": "32"
    },
    "ap_done": {
      "dir": "out",
      "width": "1"
    },
    "ap_start": {
      "dir": "in",
      "width": "1"
    },
    "ap_ready": {
      "dir": "out",
      "width": "1"
    },
    "ap_idle": {
      "dir": "out",
      "width": "1"
    }
  },
  "CPorts": {
    "inp1_img": {
      "interfaceRef": "inp1_img",
      "dir": "in"
    },
    "inp2_img": {
      "interfaceRef": "inp2_img",
      "dir": "in"
    },
    "vx_img": {
      "interfaceRef": "vx_img",
      "dir": "out",
      "firstOutLatency": "26"
    },
    "vy_img": {
      "interfaceRef": "vy_img",
      "dir": "out",
      "firstOutLatency": "26"
    },
    "height": {
      "interfaceRef": "height",
      "dir": "in",
      "dataWidth": "16",
      "handshakeRef": "ap_none"
    },
    "width": {
      "interfaceRef": "width",
      "dir": "in",
      "dataWidth": "16",
      "handshakeRef": "ap_none"
    },
    "ap_return": {
      "interfaceRef": "ap_return",
      "dir": "out",
      "dataWidth": "32"
    },
    "ap_ctrl": {
      "interfaceRef": "ap_ctrl",
      "dir": "out"
    }
  },
  "ModuleInfo": {
    "Hierarchy": {
      "ModuleName": "hls_LK",
      "Instances": [
        {
          "ModuleName": "hls_ComputeVectors",
          "InstanceName": "hls_ComputeVectors_U0"
        },
        {
          "ModuleName": "hls_twoIsotropicFilt",
          "InstanceName": "hls_twoIsotropicFilt_U0",
          "Instances": [
            {
              "ModuleName": "hls_isotropic_kernel",
              "InstanceName": "grp_hls_isotropic_kernel_fu_543"
            },
            {
              "ModuleName": "hls_isotropic_kernel",
              "InstanceName": "grp_hls_isotropic_kernel_fu_572"
            }
          ]
        },
        {
          "ModuleName": "hls_ComputeIntegrals",
          "InstanceName": "hls_ComputeIntegrals_U0"
        },
        {
          "ModuleName": "hls_SpatialTemporalD",
          "InstanceName": "hls_SpatialTemporalD_U0"
        }
      ]
    },
    "Metrics": {
      "hls_isotropic_kernel": {
        "Latency": {
          "LatencyBest": "1",
          "LatencyAvg": "1",
          "LatencyWorst": "1",
          "PipelineII": "1",
          "PipelineDepth": "2",
          "PipelineType": "function"
        },
        "Timing": {
          "Target": "10.00",
          "Uncertainty": "0.10",
          "Estimate": "9.86"
        },
        "Area": {
          "FF": "120",
          "LUT": "1268",
          "BRAM_18K": "0",
          "DSP48E": "0"
        }
      },
      "hls_twoIsotropicFilt": {
        "Latency": {
          "LatencyBest": "1",
          "LatencyAvg": "78241",
          "LatencyWorst": "310081",
          "PipelineIIMin": "1",
          "PipelineIIMax": "310081",
          "PipelineII": "1 ~ 310081",
          "PipelineDepth": "",
          "PipelineType": "none"
        },
        "Timing": {
          "Target": "10.00",
          "Uncertainty": "0.10",
          "Estimate": "9.86"
        },
        "Loops": [{
            "Name": "L1",
            "TripCount": "",
            "LatencyMin": "0",
            "LatencyMax": "310080",
            "Latency": "0 ~ 310080",
            "PipelineII": "",
            "PipelineDepthMin": "5",
            "PipelineDepthMax": "646",
            "PipelineDepth": "5 ~ 646",
            "Loops": [{
                "Name": "L2",
                "TripCount": "",
                "LatencyMin": "2",
                "LatencyMax": "643",
                "Latency": "2 ~ 643",
                "PipelineII": "1",
                "PipelineDepth": "5"
              }]
          }],
        "Area": {
          "BRAM_18K": "16",
          "FF": "1367",
          "LUT": "3068",
          "DSP48E": "0"
        }
      },
      "hls_SpatialTemporalD": {
        "Latency": {
          "LatencyBest": "307206",
          "LatencyAvg": "",
          "LatencyWorst": "2073606",
          "PipelineIIMin": "307206",
          "PipelineIIMax": "2073606",
          "PipelineII": "307206 ~ 2073606",
          "PipelineDepth": "",
          "PipelineType": "none"
        },
        "Timing": {
          "Target": "10.00",
          "Uncertainty": "0.10",
          "Estimate": "8.43"
        },
        "Loops": [{
            "Name": "L1_L2",
            "TripCount": "",
            "LatencyMin": "307203",
            "LatencyMax": "2073603",
            "Latency": "307203 ~ 2073603",
            "PipelineII": "1",
            "PipelineDepth": "5"
          }],
        "Area": {
          "BRAM_18K": "12",
          "DSP48E": "3",
          "FF": "1057",
          "LUT": "1020"
        }
      },
      "hls_ComputeIntegrals": {
        "Latency": {
          "LatencyBest": "307207",
          "LatencyAvg": "",
          "LatencyWorst": "2073607",
          "PipelineIIMin": "307207",
          "PipelineIIMax": "2073607",
          "PipelineII": "307207 ~ 2073607",
          "PipelineDepth": "",
          "PipelineType": "none"
        },
        "Timing": {
          "Target": "10.00",
          "Uncertainty": "0.10",
          "Estimate": "10.39"
        },
        "Loops": [{
            "Name": "L1_L2",
            "TripCount": "",
            "LatencyMin": "307204",
            "LatencyMax": "2073604",
            "Latency": "307204 ~ 2073604",
            "PipelineII": "1",
            "PipelineDepth": "6"
          }],
        "Area": {
          "BRAM_18K": "50",
          "DSP48E": "56",
          "FF": "3831",
          "LUT": "1800"
        }
      },
      "hls_ComputeVectors": {
        "Latency": {
          "LatencyBest": "307226",
          "LatencyAvg": "",
          "LatencyWorst": "2073626",
          "PipelineIIMin": "307226",
          "PipelineIIMax": "2073626",
          "PipelineII": "307226 ~ 2073626",
          "PipelineDepth": "",
          "PipelineType": "none"
        },
        "Timing": {
          "Target": "10.00",
          "Uncertainty": "0.10",
          "Estimate": "9.32"
        },
        "Loops": [{
            "Name": "L1_L2",
            "TripCount": "",
            "LatencyMin": "307224",
            "LatencyMax": "2073624",
            "Latency": "307224 ~ 2073624",
            "PipelineII": "1",
            "PipelineDepth": "26"
          }],
        "Area": {
          "BRAM_18K": "0",
          "DSP48E": "33",
          "FF": "3199",
          "LUT": "5912"
        }
      },
      "hls_LK": {
        "Latency": {
          "LatencyBest": "307239",
          "LatencyAvg": "",
          "LatencyWorst": "2073639",
          "PipelineIIMin": "307227",
          "PipelineIIMax": "2073627",
          "PipelineII": "307227 ~ 2073627",
          "PipelineDepth": "",
          "PipelineType": "dataflow"
        },
        "Timing": {
          "Target": "10.00",
          "Uncertainty": "0.10",
          "Estimate": "10.39"
        },
        "Area": {
          "BRAM_18K": "78",
          "DSP48E": "92",
          "FF": "9544",
          "LUT": "12353"
        }
      }
    }
  },
  "GenData": {
    "DataVersion": "0.1",
    "Time": "2018-09-20 12:50:54 +0200",
    "ToolName": "vivado_hls",
    "ToolVersion": "2018.1"
  }
}
