<?xml version="1.0" encoding="UTF-8"?>
<vivadoHLSLog:LogRoot xmlns:vivadoHLSLog="www.xilinx.com/vivadoHLSLog">
  <errorLogs>
    <logs>
      <synLog/>
      <simLog/>
    </logs>
  </errorLogs>
  <warningLogs>
    <logs>
      <synLog>
        <logs message="WARNING: [RTGEN 206-101] Global scalar 'areaEventThrBak' will not be exposed as RTL port." projectName="topParseEvents" solutionName="solution1" date="2018-10-23T22:53:18.524+0200" type="Warning"/>
        <logs message="WARNING: [RTGEN 206-101] Global scalar 'oldIdx_V' will not be exposed as RTL port." projectName="topParseEvents" solutionName="solution1" date="2018-10-23T22:53:18.511+0200" type="Warning"/>
        <logs message="WARNING: [RTGEN 206-101] Setting dangling out port 'dataflow_parent_loop_1/m_axi_eventSlice_RREADY' to 0." projectName="topParseEvents" solutionName="solution1" date="2018-10-23T22:53:17.448+0200" type="Warning"/>
        <logs message="WARNING: [RTGEN 206-101] Setting dangling out port 'dataflow_parent_loop_1/m_axi_eventSlice_ARUSER' to 0." projectName="topParseEvents" solutionName="solution1" date="2018-10-23T22:53:17.425+0200" type="Warning"/>
        <logs message="WARNING: [RTGEN 206-101] Setting dangling out port 'dataflow_parent_loop_1/m_axi_eventSlice_ARREGION' to 0." projectName="topParseEvents" solutionName="solution1" date="2018-10-23T22:53:17.412+0200" type="Warning"/>
        <logs message="WARNING: [RTGEN 206-101] Setting dangling out port 'dataflow_parent_loop_1/m_axi_eventSlice_ARQOS' to 0." projectName="topParseEvents" solutionName="solution1" date="2018-10-23T22:53:17.398+0200" type="Warning"/>
        <logs message="WARNING: [RTGEN 206-101] Setting dangling out port 'dataflow_parent_loop_1/m_axi_eventSlice_ARPROT' to 0." projectName="topParseEvents" solutionName="solution1" date="2018-10-23T22:53:17.380+0200" type="Warning"/>
        <logs message="WARNING: [RTGEN 206-101] Setting dangling out port 'dataflow_parent_loop_1/m_axi_eventSlice_ARCACHE' to 0." projectName="topParseEvents" solutionName="solution1" date="2018-10-23T22:53:17.367+0200" type="Warning"/>
        <logs message="WARNING: [RTGEN 206-101] Setting dangling out port 'dataflow_parent_loop_1/m_axi_eventSlice_ARLOCK' to 0." projectName="topParseEvents" solutionName="solution1" date="2018-10-23T22:53:17.356+0200" type="Warning"/>
        <logs message="WARNING: [RTGEN 206-101] Setting dangling out port 'dataflow_parent_loop_1/m_axi_eventSlice_ARBURST' to 0." projectName="topParseEvents" solutionName="solution1" date="2018-10-23T22:53:17.343+0200" type="Warning"/>
        <logs message="WARNING: [RTGEN 206-101] Setting dangling out port 'dataflow_parent_loop_1/m_axi_eventSlice_ARSIZE' to 0." projectName="topParseEvents" solutionName="solution1" date="2018-10-23T22:53:17.330+0200" type="Warning"/>
        <logs message="WARNING: [RTGEN 206-101] Setting dangling out port 'dataflow_parent_loop_1/m_axi_eventSlice_ARLEN' to 0." projectName="topParseEvents" solutionName="solution1" date="2018-10-23T22:53:17.316+0200" type="Warning"/>
        <logs message="WARNING: [RTGEN 206-101] Setting dangling out port 'dataflow_parent_loop_1/m_axi_eventSlice_ARID' to 0." projectName="topParseEvents" solutionName="solution1" date="2018-10-23T22:53:17.305+0200" type="Warning"/>
        <logs message="WARNING: [RTGEN 206-101] Setting dangling out port 'dataflow_parent_loop_1/m_axi_eventSlice_ARADDR' to 0." projectName="topParseEvents" solutionName="solution1" date="2018-10-23T22:53:17.297+0200" type="Warning"/>
        <logs message="WARNING: [RTGEN 206-101] Setting dangling out port 'dataflow_parent_loop_1/m_axi_eventSlice_ARVALID' to 0." projectName="topParseEvents" solutionName="solution1" date="2018-10-23T22:53:17.285+0200" type="Warning"/>
        <logs message="WARNING: [RTGEN 206-101] Setting dangling out port 'dataflow_in_loop_par/m_axi_eventSlice_RREADY' to 0." projectName="topParseEvents" solutionName="solution1" date="2018-10-23T22:53:15.942+0200" type="Warning"/>
        <logs message="WARNING: [RTGEN 206-101] Setting dangling out port 'dataflow_in_loop_par/m_axi_eventSlice_ARUSER' to 0." projectName="topParseEvents" solutionName="solution1" date="2018-10-23T22:53:15.906+0200" type="Warning"/>
        <logs message="WARNING: [RTGEN 206-101] Setting dangling out port 'dataflow_in_loop_par/m_axi_eventSlice_ARREGION' to 0." projectName="topParseEvents" solutionName="solution1" date="2018-10-23T22:53:15.894+0200" type="Warning"/>
        <logs message="WARNING: [RTGEN 206-101] Setting dangling out port 'dataflow_in_loop_par/m_axi_eventSlice_ARQOS' to 0." projectName="topParseEvents" solutionName="solution1" date="2018-10-23T22:53:15.883+0200" type="Warning"/>
      </synLog>
      <simLog>
        <logs message="WARNING: Hls::stream 'thresholdStream' contains leftover data, which may result in RTL simulation hanging.&#xD;&#xA;Test 19 passed.&#xD;&#xA;&#xD;&#xA;*** TEST PASSED ***" projectName="topParseEvents" solutionName="solution1" date="2018-10-23T22:58:04.291+0200" type="Warning"/>
        <logs message="WARNING: Hls::stream 'thresholdStream' contains leftover data, which may result in RTL simulation hanging.&#xD;&#xA;Test 18 passed.&#xD;&#xA;&#xD;&#xA;Test 19:&#xD;&#xA;Current Event packet's event number is: 500&#xD;&#xA;Rotated successfully from SW!!!!&#xD;&#xA;x is: 42&#x9; y is: 49&#x9; idx is: 1&#xD;&#xA;Rotated successfully from SW!!!!&#xD;&#xA;x is: 50&#x9; y is: 54&#x9; idx is: 0&#xD;&#xA;Rotated successfully from SW!!!!&#xD;&#xA;x is: 56&#x9; y is: 58&#x9; idx is: 3&#xD;&#xA;Rotated successfully from SW!!!!&#xD;&#xA;x is: 59&#x9; y is: 33&#x9; idx is: 2&#xD;&#xA;Rotated successfully from HW!!!!&#xD;&#xA;x is: 42&#x9; y is: 49&#x9; idx is: 1&#xD;&#xA;Rotated successfully from HW!!!!&#xD;&#xA;x is: 50&#x9; y is: 54&#x9; idx is: 0&#xD;&#xA;Rotated successfully from HW!!!!&#xD;&#xA;x is: 56&#x9; y is: 58&#x9; idx is: 3&#xD;&#xA;Rotated successfully from HW!!!!&#xD;&#xA;x is: 59&#x9; y is: 33&#x9; idx is: 2" projectName="topParseEvents" solutionName="solution1" date="2018-10-23T22:58:04.100+0200" type="Warning"/>
        <logs message="WARNING: Hls::stream 'thresholdStream' contains leftover data, which may result in RTL simulation hanging.&#xD;&#xA;Test 17 passed.&#xD;&#xA;&#xD;&#xA;Test 18:&#xD;&#xA;Current Event packet's event number is: 500&#xD;&#xA;Rotated successfully from SW!!!!&#xD;&#xA;x is: 39&#x9; y is: 34&#x9; idx is: 1&#xD;&#xA;Rotated successfully from SW!!!!&#xD;&#xA;x is: 44&#x9; y is: 44&#x9; idx is: 0&#xD;&#xA;Rotated successfully from SW!!!!&#xD;&#xA;x is: 55&#x9; y is: 38&#x9; idx is: 3&#xD;&#xA;Rotated successfully from SW!!!!&#xD;&#xA;x is: 42&#x9; y is: 15&#x9; idx is: 2&#xD;&#xA;Rotated successfully from HW!!!!&#xD;&#xA;x is: 39&#x9; y is: 34&#x9; idx is: 1&#xD;&#xA;Rotated successfully from HW!!!!&#xD;&#xA;x is: 44&#x9; y is: 44&#x9; idx is: 0&#xD;&#xA;Rotated successfully from HW!!!!&#xD;&#xA;x is: 55&#x9; y is: 38&#x9; idx is: 3&#xD;&#xA;Rotated successfully from HW!!!!&#xD;&#xA;x is: 42&#x9; y is: 15&#x9; idx is: 2" projectName="topParseEvents" solutionName="solution1" date="2018-10-23T22:58:00.975+0200" type="Warning"/>
        <logs message="WARNING: Hls::stream 'thresholdStream' contains leftover data, which may result in RTL simulation hanging.&#xD;&#xA;Test 16 passed.&#xD;&#xA;&#xD;&#xA;Test 17:&#xD;&#xA;Current Event packet's event number is: 500&#xD;&#xA;Rotated successfully from SW!!!!&#xD;&#xA;x is: 23&#x9; y is: 33&#x9; idx is: 2&#xD;&#xA;Rotated successfully from SW!!!!&#xD;&#xA;x is: 32&#x9; y is: 36&#x9; idx is: 1&#xD;&#xA;Rotated successfully from SW!!!!&#xD;&#xA;x is: 38&#x9; y is: 34&#x9; idx is: 0&#xD;&#xA;Rotated successfully from SW!!!!&#xD;&#xA;x is: 36&#x9; y is: 56&#x9; idx is: 3&#xD;&#xA;Rotated successfully from SW!!!!&#xD;&#xA;x is: 40&#x9; y is: 39&#x9; idx is: 2&#xD;&#xA;Rotated successfully from HW!!!!&#xD;&#xA;x is: 23&#x9; y is: 33&#x9; idx is: 2&#xD;&#xA;Rotated successfully from HW!!!!&#xD;&#xA;x is: 32&#x9; y is: 36&#x9; idx is: 1&#xD;&#xA;Rotated successfully from HW!!!!&#xD;&#xA;x is: 38&#x9; y is: 34&#x9; idx is: 0&#xD;&#xA;Rotated successfully from HW!!!!&#xD;&#xA;x is: 36&#x9; y is: 56&#x9; idx is: 3&#xD;&#xA;Rotated successfully from HW!!!!&#xD;&#xA;x is: 40&#x9; y is: 39&#x9; idx is: 2" projectName="topParseEvents" solutionName="solution1" date="2018-10-23T22:57:57.899+0200" type="Warning"/>
        <logs message="WARNING: Hls::stream 'thresholdStream' contains leftover data, which may result in RTL simulation hanging.&#xD;&#xA;Test 15 passed.&#xD;&#xA;&#xD;&#xA;Test 16:&#xD;&#xA;Current Event packet's event number is: 500&#xD;&#xA;Rotated successfully from SW!!!!&#xD;&#xA;x is: 51&#x9; y is: 53&#x9; idx is: 2&#xD;&#xA;Rotated successfully from SW!!!!&#xD;&#xA;x is: 33&#x9; y is: 26&#x9; idx is: 1&#xD;&#xA;Rotated successfully from SW!!!!&#xD;&#xA;x is: 28&#x9; y is: 56&#x9; idx is: 0&#xD;&#xA;Rotated successfully from SW!!!!&#xD;&#xA;x is: 52&#x9; y is: 36&#x9; idx is: 3&#xD;&#xA;Rotated successfully from HW!!!!&#xD;&#xA;x is: 51&#x9; y is: 53&#x9; idx is: 2&#xD;&#xA;Rotated successfully from HW!!!!&#xD;&#xA;x is: 33&#x9; y is: 26&#x9; idx is: 1&#xD;&#xA;Rotated successfully from HW!!!!&#xD;&#xA;x is: 28&#x9; y is: 56&#x9; idx is: 0&#xD;&#xA;Rotated successfully from HW!!!!&#xD;&#xA;x is: 52&#x9; y is: 36&#x9; idx is: 3" projectName="topParseEvents" solutionName="solution1" date="2018-10-23T22:57:54.784+0200" type="Warning"/>
        <logs message="WARNING: Hls::stream 'thresholdStream' contains leftover data, which may result in RTL simulation hanging.&#xD;&#xA;Test 14 passed.&#xD;&#xA;&#xD;&#xA;Test 15:&#xD;&#xA;Current Event packet's event number is: 500&#xD;&#xA;Rotated successfully from SW!!!!&#xD;&#xA;x is: 49&#x9; y is: 20&#x9; idx is: 2&#xD;&#xA;Rotated successfully from SW!!!!&#xD;&#xA;x is: 54&#x9; y is: 48&#x9; idx is: 1&#xD;&#xA;Rotated successfully from SW!!!!&#xD;&#xA;x is: 44&#x9; y is: 45&#x9; idx is: 0&#xD;&#xA;Rotated successfully from SW!!!!&#xD;&#xA;x is: 53&#x9; y is: 46&#x9; idx is: 3&#xD;&#xA;Rotated successfully from HW!!!!&#xD;&#xA;x is: 49&#x9; y is: 20&#x9; idx is: 2&#xD;&#xA;Rotated successfully from HW!!!!&#xD;&#xA;x is: 54&#x9; y is: 48&#x9; idx is: 1&#xD;&#xA;Rotated successfully from HW!!!!&#xD;&#xA;x is: 44&#x9; y is: 45&#x9; idx is: 0&#xD;&#xA;Rotated successfully from HW!!!!&#xD;&#xA;x is: 53&#x9; y is: 46&#x9; idx is: 3" projectName="topParseEvents" solutionName="solution1" date="2018-10-23T22:57:51.661+0200" type="Warning"/>
        <logs message="WARNING: Hls::stream 'thresholdStream' contains leftover data, which may result in RTL simulation hanging.&#xD;&#xA;Test 13 passed.&#xD;&#xA;&#xD;&#xA;Test 14:&#xD;&#xA;Current Event packet's event number is: 500&#xD;&#xA;Rotated successfully from SW!!!!&#xD;&#xA;x is: 42&#x9; y is: 56&#x9; idx is: 1&#xD;&#xA;Rotated successfully from SW!!!!&#xD;&#xA;x is: 37&#x9; y is: 25&#x9; idx is: 0&#xD;&#xA;Rotated successfully from SW!!!!&#xD;&#xA;x is: 50&#x9; y is: 39&#x9; idx is: 3&#xD;&#xA;Rotated successfully from HW!!!!&#xD;&#xA;x is: 42&#x9; y is: 56&#x9; idx is: 1&#xD;&#xA;Rotated successfully from HW!!!!&#xD;&#xA;x is: 37&#x9; y is: 25&#x9; idx is: 0&#xD;&#xA;Rotated successfully from HW!!!!&#xD;&#xA;x is: 50&#x9; y is: 39&#x9; idx is: 3" projectName="topParseEvents" solutionName="solution1" date="2018-10-23T22:57:48.489+0200" type="Warning"/>
        <logs message="WARNING: Hls::stream 'thresholdStream' contains leftover data, which may result in RTL simulation hanging.&#xD;&#xA;Test 12 passed.&#xD;&#xA;&#xD;&#xA;Test 13:&#xD;&#xA;Current Event packet's event number is: 500&#xD;&#xA;Rotated successfully from SW!!!!&#xD;&#xA;x is: 51&#x9; y is: 51&#x9; idx is: 2&#xD;&#xA;Rotated successfully from SW!!!!&#xD;&#xA;x is: 48&#x9; y is: 38&#x9; idx is: 1&#xD;&#xA;Rotated successfully from SW!!!!&#xD;&#xA;x is: 56&#x9; y is: 52&#x9; idx is: 0&#xD;&#xA;Rotated successfully from SW!!!!&#xD;&#xA;x is: 51&#x9; y is: 52&#x9; idx is: 3&#xD;&#xA;Rotated successfully from SW!!!!&#xD;&#xA;x is: 52&#x9; y is: 54&#x9; idx is: 2&#xD;&#xA;Rotated successfully from HW!!!!&#xD;&#xA;x is: 51&#x9; y is: 51&#x9; idx is: 2&#xD;&#xA;Rotated successfully from HW!!!!&#xD;&#xA;x is: 48&#x9; y is: 38&#x9; idx is: 1&#xD;&#xA;Rotated successfully from HW!!!!&#xD;&#xA;x is: 56&#x9; y is: 52&#x9; idx is: 0&#xD;&#xA;Rotated successfully from HW!!!!&#xD;&#xA;x is: 51&#x9; y is: 52&#x9; idx is: 3&#xD;&#xA;Rotated successfully from HW!!!!&#xD;&#xA;x is: 52&#x9; y is: 54&#x9; idx is: 2" projectName="topParseEvents" solutionName="solution1" date="2018-10-23T22:57:45.362+0200" type="Warning"/>
        <logs message="WARNING: Hls::stream 'thresholdStream' contains leftover data, which may result in RTL simulation hanging.&#xD;&#xA;Test 11 passed.&#xD;&#xA;&#xD;&#xA;Test 12:&#xD;&#xA;Current Event packet's event number is: 500&#xD;&#xA;Rotated successfully from SW!!!!&#xD;&#xA;x is: 49&#x9; y is: 52&#x9; idx is: 2&#xD;&#xA;Rotated successfully from SW!!!!&#xD;&#xA;x is: 26&#x9; y is: 42&#x9; idx is: 1&#xD;&#xA;Rotated successfully from SW!!!!&#xD;&#xA;x is: 41&#x9; y is: 47&#x9; idx is: 0&#xD;&#xA;Rotated successfully from SW!!!!&#xD;&#xA;x is: 54&#x9; y is: 16&#x9; idx is: 3&#xD;&#xA;Rotated successfully from HW!!!!&#xD;&#xA;x is: 49&#x9; y is: 52&#x9; idx is: 2&#xD;&#xA;Rotated successfully from HW!!!!&#xD;&#xA;x is: 26&#x9; y is: 42&#x9; idx is: 1&#xD;&#xA;Rotated successfully from HW!!!!&#xD;&#xA;x is: 41&#x9; y is: 47&#x9; idx is: 0&#xD;&#xA;Rotated successfully from HW!!!!&#xD;&#xA;x is: 54&#x9; y is: 16&#x9; idx is: 3" projectName="topParseEvents" solutionName="solution1" date="2018-10-23T22:57:42.324+0200" type="Warning"/>
        <logs message="WARNING: Hls::stream 'thresholdStream' contains leftover data, which may result in RTL simulation hanging.&#xD;&#xA;Test 10 passed.&#xD;&#xA;&#xD;&#xA;Test 11:&#xD;&#xA;Current Event packet's event number is: 500&#xD;&#xA;Rotated successfully from SW!!!!&#xD;&#xA;x is: 46&#x9; y is: 33&#x9; idx is: 2&#xD;&#xA;Rotated successfully from SW!!!!&#xD;&#xA;x is: 39&#x9; y is: 54&#x9; idx is: 1&#xD;&#xA;Rotated successfully from SW!!!!&#xD;&#xA;x is: 37&#x9; y is: 35&#x9; idx is: 0&#xD;&#xA;Rotated successfully from SW!!!!&#xD;&#xA;x is: 49&#x9; y is: 50&#x9; idx is: 3&#xD;&#xA;Rotated successfully from HW!!!!&#xD;&#xA;x is: 46&#x9; y is: 33&#x9; idx is: 2&#xD;&#xA;Rotated successfully from HW!!!!&#xD;&#xA;x is: 39&#x9; y is: 54&#x9; idx is: 1&#xD;&#xA;Rotated successfully from HW!!!!&#xD;&#xA;x is: 37&#x9; y is: 35&#x9; idx is: 0&#xD;&#xA;Rotated successfully from HW!!!!&#xD;&#xA;x is: 49&#x9; y is: 50&#x9; idx is: 3" projectName="topParseEvents" solutionName="solution1" date="2018-10-23T22:57:39.201+0200" type="Warning"/>
        <logs message="WARNING: Hls::stream 'thresholdStream' contains leftover data, which may result in RTL simulation hanging.&#xD;&#xA;Test 9 passed.&#xD;&#xA;&#xD;&#xA;Test 10:&#xD;&#xA;Current Event packet's event number is: 500&#xD;&#xA;Rotated successfully from SW!!!!&#xD;&#xA;x is: 39&#x9; y is: 42&#x9; idx is: 1&#xD;&#xA;Rotated successfully from SW!!!!&#xD;&#xA;x is: 40&#x9; y is: 32&#x9; idx is: 0&#xD;&#xA;Rotated successfully from SW!!!!&#xD;&#xA;x is: 57&#x9; y is: 51&#x9; idx is: 3&#xD;&#xA;Rotated successfully from HW!!!!&#xD;&#xA;x is: 39&#x9; y is: 42&#x9; idx is: 1&#xD;&#xA;Rotated successfully from HW!!!!&#xD;&#xA;x is: 40&#x9; y is: 32&#x9; idx is: 0&#xD;&#xA;Rotated successfully from HW!!!!&#xD;&#xA;x is: 57&#x9; y is: 51&#x9; idx is: 3" projectName="topParseEvents" solutionName="solution1" date="2018-10-23T22:57:36.131+0200" type="Warning"/>
        <logs message="WARNING: Hls::stream 'thresholdStream' contains leftover data, which may result in RTL simulation hanging.&#xD;&#xA;Test 8 passed.&#xD;&#xA;&#xD;&#xA;Test 9:&#xD;&#xA;Current Event packet's event number is: 500&#xD;&#xA;Rotated successfully from SW!!!!&#xD;&#xA;x is: 33&#x9; y is: 54&#x9; idx is: 1&#xD;&#xA;Rotated successfully from SW!!!!&#xD;&#xA;x is: 15&#x9; y is: 52&#x9; idx is: 0&#xD;&#xA;Rotated successfully from SW!!!!&#xD;&#xA;x is: 29&#x9; y is: 52&#x9; idx is: 3&#xD;&#xA;Rotated successfully from SW!!!!&#xD;&#xA;x is: 54&#x9; y is: 57&#x9; idx is: 2&#xD;&#xA;Rotated successfully from HW!!!!&#xD;&#xA;x is: 33&#x9; y is: 54&#x9; idx is: 1&#xD;&#xA;Rotated successfully from HW!!!!&#xD;&#xA;x is: 15&#x9; y is: 52&#x9; idx is: 0&#xD;&#xA;Rotated successfully from HW!!!!&#xD;&#xA;x is: 29&#x9; y is: 52&#x9; idx is: 3&#xD;&#xA;Rotated successfully from HW!!!!&#xD;&#xA;x is: 54&#x9; y is: 57&#x9; idx is: 2" projectName="topParseEvents" solutionName="solution1" date="2018-10-23T22:57:33.112+0200" type="Warning"/>
        <logs message="WARNING: Hls::stream 'thresholdStream' contains leftover data, which may result in RTL simulation hanging.&#xD;&#xA;Test 7 passed.&#xD;&#xA;&#xD;&#xA;Test 8:&#xD;&#xA;Current Event packet's event number is: 500&#xD;&#xA;Rotated successfully from SW!!!!&#xD;&#xA;x is: 53&#x9; y is: 36&#x9; idx is: 1&#xD;&#xA;Rotated successfully from SW!!!!&#xD;&#xA;x is: 47&#x9; y is: 51&#x9; idx is: 0&#xD;&#xA;Rotated successfully from SW!!!!&#xD;&#xA;x is: 56&#x9; y is: 49&#x9; idx is: 3&#xD;&#xA;Rotated successfully from SW!!!!&#xD;&#xA;x is: 39&#x9; y is: 39&#x9; idx is: 2&#xD;&#xA;Rotated successfully from HW!!!!&#xD;&#xA;x is: 53&#x9; y is: 36&#x9; idx is: 1&#xD;&#xA;Rotated successfully from HW!!!!&#xD;&#xA;x is: 47&#x9; y is: 51&#x9; idx is: 0&#xD;&#xA;Rotated successfully from HW!!!!&#xD;&#xA;x is: 56&#x9; y is: 49&#x9; idx is: 3&#xD;&#xA;Rotated successfully from HW!!!!&#xD;&#xA;x is: 39&#x9; y is: 39&#x9; idx is: 2" projectName="topParseEvents" solutionName="solution1" date="2018-10-23T22:57:29.840+0200" type="Warning"/>
        <logs message="WARNING: Hls::stream 'thresholdStream' contains leftover data, which may result in RTL simulation hanging.&#xD;&#xA;Test 6 passed.&#xD;&#xA;&#xD;&#xA;Test 7:&#xD;&#xA;Current Event packet's event number is: 500&#xD;&#xA;Rotated successfully from SW!!!!&#xD;&#xA;x is: 35&#x9; y is: 32&#x9; idx is: 0&#xD;&#xA;Rotated successfully from SW!!!!&#xD;&#xA;x is: 12&#x9; y is: 59&#x9; idx is: 3&#xD;&#xA;Rotated successfully from SW!!!!&#xD;&#xA;x is: 37&#x9; y is: 42&#x9; idx is: 2&#xD;&#xA;Rotated successfully from HW!!!!&#xD;&#xA;x is: 35&#x9; y is: 32&#x9; idx is: 0&#xD;&#xA;Rotated successfully from HW!!!!&#xD;&#xA;x is: 12&#x9; y is: 59&#x9; idx is: 3&#xD;&#xA;Rotated successfully from HW!!!!&#xD;&#xA;x is: 37&#x9; y is: 42&#x9; idx is: 2" projectName="topParseEvents" solutionName="solution1" date="2018-10-23T22:57:26.736+0200" type="Warning"/>
        <logs message="WARNING: Hls::stream 'thresholdStream' contains leftover data, which may result in RTL simulation hanging.&#xD;&#xA;Test 5 passed.&#xD;&#xA;&#xD;&#xA;Test 6:&#xD;&#xA;Current Event packet's event number is: 500&#xD;&#xA;Rotated successfully from SW!!!!&#xD;&#xA;x is: 59&#x9; y is: 48&#x9; idx is: 3&#xD;&#xA;Rotated successfully from SW!!!!&#xD;&#xA;x is: 17&#x9; y is: 39&#x9; idx is: 2&#xD;&#xA;Rotated successfully from SW!!!!&#xD;&#xA;x is: 34&#x9; y is: 34&#x9; idx is: 1&#xD;&#xA;Rotated successfully from HW!!!!&#xD;&#xA;x is: 59&#x9; y is: 48&#x9; idx is: 3&#xD;&#xA;Rotated successfully from HW!!!!&#xD;&#xA;x is: 17&#x9; y is: 39&#x9; idx is: 2&#xD;&#xA;Rotated successfully from HW!!!!&#xD;&#xA;x is: 34&#x9; y is: 34&#x9; idx is: 1" projectName="topParseEvents" solutionName="solution1" date="2018-10-23T22:57:23.657+0200" type="Warning"/>
        <logs message="WARNING: Hls::stream 'thresholdStream' contains leftover data, which may result in RTL simulation hanging.&#xD;&#xA;Test 4 passed.&#xD;&#xA;&#xD;&#xA;Test 5:&#xD;&#xA;Current Event packet's event number is: 500&#xD;&#xA;Rotated successfully from SW!!!!&#xD;&#xA;x is: 49&#x9; y is: 55&#x9; idx is: 3&#xD;&#xA;Rotated successfully from SW!!!!&#xD;&#xA;x is: 37&#x9; y is: 36&#x9; idx is: 2&#xD;&#xA;Rotated successfully from SW!!!!&#xD;&#xA;x is: 33&#x9; y is: 48&#x9; idx is: 1&#xD;&#xA;Rotated successfully from SW!!!!&#xD;&#xA;x is: 33&#x9; y is: 55&#x9; idx is: 0&#xD;&#xA;Rotated successfully from HW!!!!&#xD;&#xA;x is: 49&#x9; y is: 55&#x9; idx is: 3&#xD;&#xA;Rotated successfully from HW!!!!&#xD;&#xA;x is: 37&#x9; y is: 36&#x9; idx is: 2&#xD;&#xA;Rotated successfully from HW!!!!&#xD;&#xA;x is: 33&#x9; y is: 48&#x9; idx is: 1&#xD;&#xA;Rotated successfully from HW!!!!&#xD;&#xA;x is: 33&#x9; y is: 55&#x9; idx is: 0" projectName="topParseEvents" solutionName="solution1" date="2018-10-23T22:57:20.548+0200" type="Warning"/>
        <logs message="WARNING: Hls::stream 'thresholdStream' contains leftover data, which may result in RTL simulation hanging.&#xD;&#xA;Test 3 passed.&#xD;&#xA;&#xD;&#xA;Test 4:&#xD;&#xA;Current Event packet's event number is: 500&#xD;&#xA;Rotated successfully from SW!!!!&#xD;&#xA;x is: 34&#x9; y is: 55&#x9; idx is: 3&#xD;&#xA;Rotated successfully from SW!!!!&#xD;&#xA;x is: 45&#x9; y is: 47&#x9; idx is: 2&#xD;&#xA;Rotated successfully from SW!!!!&#xD;&#xA;x is: 54&#x9; y is: 59&#x9; idx is: 1&#xD;&#xA;Rotated successfully from SW!!!!&#xD;&#xA;x is: 45&#x9; y is: 40&#x9; idx is: 0&#xD;&#xA;Rotated successfully from HW!!!!&#xD;&#xA;x is: 34&#x9; y is: 55&#x9; idx is: 3&#xD;&#xA;Rotated successfully from HW!!!!&#xD;&#xA;x is: 45&#x9; y is: 47&#x9; idx is: 2&#xD;&#xA;Rotated successfully from HW!!!!&#xD;&#xA;x is: 54&#x9; y is: 59&#x9; idx is: 1&#xD;&#xA;Rotated successfully from HW!!!!&#xD;&#xA;x is: 45&#x9; y is: 40&#x9; idx is: 0" projectName="topParseEvents" solutionName="solution1" date="2018-10-23T22:57:17.438+0200" type="Warning"/>
        <logs message="WARNING: Hls::stream 'thresholdStream' contains leftover data, which may result in RTL simulation hanging.&#xD;&#xA;Test 2 passed.&#xD;&#xA;&#xD;&#xA;Test 3:&#xD;&#xA;Current Event packet's event number is: 500&#xD;&#xA;Rotated successfully from SW!!!!&#xD;&#xA;x is: 29&#x9; y is: 46&#x9; idx is: 2&#xD;&#xA;Rotated successfully from SW!!!!&#xD;&#xA;x is: 54&#x9; y is: 50&#x9; idx is: 1&#xD;&#xA;Rotated successfully from SW!!!!&#xD;&#xA;x is: 44&#x9; y is: 37&#x9; idx is: 0&#xD;&#xA;Rotated successfully from HW!!!!&#xD;&#xA;x is: 29&#x9; y is: 46&#x9; idx is: 2&#xD;&#xA;Rotated successfully from HW!!!!&#xD;&#xA;x is: 54&#x9; y is: 50&#x9; idx is: 1&#xD;&#xA;Rotated successfully from HW!!!!&#xD;&#xA;x is: 44&#x9; y is: 37&#x9; idx is: 0" projectName="topParseEvents" solutionName="solution1" date="2018-10-23T22:57:14.245+0200" type="Warning"/>
        <logs message="WARNING: Hls::stream 'thresholdStream' contains leftover data, which may result in RTL simulation hanging.&#xD;&#xA;Test 1 passed.&#xD;&#xA;&#xD;&#xA;Test 2:&#xD;&#xA;Current Event packet's event number is: 500&#xD;&#xA;Rotated successfully from SW!!!!&#xD;&#xA;x is: 45&#x9; y is: 18&#x9; idx is: 2&#xD;&#xA;Rotated successfully from SW!!!!&#xD;&#xA;x is: 48&#x9; y is: 55&#x9; idx is: 1&#xD;&#xA;Rotated successfully from SW!!!!&#xD;&#xA;x is: 16&#x9; y is: 34&#x9; idx is: 0&#xD;&#xA;Rotated successfully from SW!!!!&#xD;&#xA;x is: 50&#x9; y is: 36&#x9; idx is: 3&#xD;&#xA;Rotated successfully from HW!!!!&#xD;&#xA;x is: 45&#x9; y is: 18&#x9; idx is: 2&#xD;&#xA;Rotated successfully from HW!!!!&#xD;&#xA;x is: 48&#x9; y is: 55&#x9; idx is: 1&#xD;&#xA;Rotated successfully from HW!!!!&#xD;&#xA;x is: 16&#x9; y is: 34&#x9; idx is: 0&#xD;&#xA;Rotated successfully from HW!!!!&#xD;&#xA;x is: 50&#x9; y is: 36&#x9; idx is: 3" projectName="topParseEvents" solutionName="solution1" date="2018-10-23T22:57:11.180+0200" type="Warning"/>
        <logs message="WARNING: Hls::stream 'thresholdStream' contains leftover data, which may result in RTL simulation hanging.&#xD;&#xA;Test 0 passed.&#xD;&#xA;&#xD;&#xA;Test 1:&#xD;&#xA;Current Event packet's event number is: 500&#xD;&#xA;Rotated successfully from SW!!!!&#xD;&#xA;x is: 59&#x9; y is: 44&#x9; idx is: 1&#xD;&#xA;Rotated successfully from SW!!!!&#xD;&#xA;x is: 50&#x9; y is: 49&#x9; idx is: 0&#xD;&#xA;Rotated successfully from SW!!!!&#xD;&#xA;x is: 59&#x9; y is: 34&#x9; idx is: 3&#xD;&#xA;Rotated successfully from HW!!!!&#xD;&#xA;x is: 59&#x9; y is: 44&#x9; idx is: 1&#xD;&#xA;Rotated successfully from HW!!!!&#xD;&#xA;x is: 50&#x9; y is: 49&#x9; idx is: 0&#xD;&#xA;Rotated successfully from HW!!!!&#xD;&#xA;x is: 59&#x9; y is: 34&#x9; idx is: 3" projectName="topParseEvents" solutionName="solution1" date="2018-10-23T22:57:08.052+0200" type="Warning"/>
        <logs message="WARNING: [COSIM 212-369] AXI_master port 'gmem' has a depth of '500'. Insufficient depth may result in simulation mismatch or freeze.&#xD;&#xA;   Build using &quot;D:/Xilinx/Vivado/2018.1/msys/bin/g++.exe&quot;&#xD;&#xA;   Compiling abmofAccel.cpp_pre.cpp.tb.cpp&#xD;&#xA;   Compiling apatb_parseEvents.cpp&#xD;&#xA;   Compiling test.cpp_pre.cpp.tb.cpp&#xD;&#xA;   Generating cosim.tv.exe" projectName="topParseEvents" solutionName="solution1" date="2018-10-23T22:57:00.275+0200" type="Warning"/>
      </simLog>
    </logs>
  </warningLogs>
</vivadoHLSLog:LogRoot>
